llama_recipes/finetuning.py
llama_recipes/configs/__init__.py
llama_recipes/configs/datasets.py
llama_recipes/configs/fsdp.py
llama_recipes/configs/peft.py
llama_recipes/configs/quantization.py
llama_recipes/configs/training.py
llama_recipes/configs/wandb.py
llama_recipes/data/__init__.py
llama_recipes/data/concatenator.py
llama_recipes/data/sampler.py
llama_recipes/data/llama_guard/__init__.py
llama_recipes/data/llama_guard/finetuning_data_formatter.py
llama_recipes/data/llama_guard/finetuning_data_formatter_example.py
llama_recipes/datasets/__init__.py
llama_recipes/datasets/alpaca_dataset.py
llama_recipes/datasets/custom_dataset.py
llama_recipes/datasets/samsum_dataset.py
llama_recipes/datasets/toxicchat_dataset.py
llama_recipes/datasets/grammar_dataset/__init__.py
llama_recipes/datasets/grammar_dataset/grammar_dataset.py
llama_recipes/inference/__init__.py
llama_recipes/inference/chat_utils.py
llama_recipes/inference/checkpoint_converter_fsdp_hf.py
llama_recipes/inference/llm.py
llama_recipes/inference/model_utils.py
llama_recipes/inference/prompt_format_utils.py
llama_recipes/inference/safety_utils.py
llama_recipes/model_checkpointing/__init__.py
llama_recipes/model_checkpointing/checkpoint_handler.py
llama_recipes/policies/__init__.py
llama_recipes/policies/activation_checkpointing_functions.py
llama_recipes/policies/anyprecision_optimizer.py
llama_recipes/policies/mixed_precision.py
llama_recipes/policies/wrapping.py
llama_recipes/tools/compare_llama_weights.py
llama_recipes/tools/convert_hf_weights_to_llama.py
llama_recipes/utils/__init__.py
llama_recipes/utils/config_utils.py
llama_recipes/utils/dataset_utils.py
llama_recipes/utils/flop_utils.py
llama_recipes/utils/fsdp_utils.py
llama_recipes/utils/memory_utils.py
llama_recipes/utils/plot_metrics.py
llama_recipes/utils/train_utils.py
llama_recipes-0.0.5.post2.dist-info/METADATA
llama_recipes-0.0.5.post2.dist-info/WHEEL
llama_recipes-0.0.5.post2.dist-info/RECORD
