Metadata-Version: 2.4
Name: llama-recipes
Version: 0.0.5.post2
Summary: This is a compatibility package to keep projects build on llama-recipes compatible with the new name llama-cookbook. If you're updating your project or starting a new one please use llama-cookbook package
Project-URL: Homepage, https://github.com/meta-llama/llama-cookbook
Project-URL: Bug Tracker, https://github.com/meta-llama/llama-cookbook/issues
Author-email: Hamid Shojanazeri <hamidnazeri@meta.com>, Matthias Reso <mreso@meta.com>, Geeta Chauhan <gchauhan@meta.com>
Classifier: License :: Other/Proprietary License
Classifier: Operating System :: OS Independent
Classifier: Programming Language :: Python :: 3
Requires-Python: >=3.8
Requires-Dist: llama-cookbook==0.0.5.post1
Provides-Extra: auditnlg
Requires-Dist: auditnlg; extra == 'auditnlg'
Provides-Extra: langchain
Requires-Dist: langchain; extra == 'langchain'
Requires-Dist: langchain-community; extra == 'langchain'
Requires-Dist: langchain-openai; extra == 'langchain'
Provides-Extra: tests
Requires-Dist: pytest-mock; extra == 'tests'
Provides-Extra: vllm
Requires-Dist: vllm; extra == 'vllm'
